missingvalues/missingValues.py
missingvalues_101703297_ucs633-1.0.1.dist-info/METADATA
missingvalues_101703297_ucs633-1.0.1.dist-info/WHEEL
missingvalues_101703297_ucs633-1.0.1.dist-info/entry_points.txt
missingvalues_101703297_ucs633-1.0.1.dist-info/top_level.txt
missingvalues_101703297_ucs633-1.0.1.dist-info/RECORD
